lume/VERSION
lume/__init__.py
lume/config/__init__.py
lume/config/check_list_or_str_item.py
lume/config/check_os_list_or_str_item.py
lume/config/config.py
lume/config/config_file_not_found_error.py
lume/config/config_file_not_valid_error.py
lume/config/dependency_config.py
lume/config/get_envs.py
lume/config/install_config.py
lume/config/required_env_error.py
lume/config/setup_config.py
lume/config/step_config.py
lume/config/uninstall_config.py
lume/src/__init__.py
lume/src/application/__init__.py
lume/src/application/cli/__init__.py
lume/src/application/cli/lume.py
lume/src/application/use_cases/__init__.py
lume/src/application/use_cases/env_manager.py
lume/src/application/use_cases/lume_use_case.py
lume/src/application/use_cases/messages.py
lume/src/application/use_cases/use_case_builder.py
lume/src/domain/__init__.py
lume/src/domain/services/__init__.py
lume/src/domain/services/executor_service.py
lume/src/domain/services/killer_service.py
lume/src/domain/services/logger.py
lume/src/domain/services/setup_service.py
lume/src/infrastructure/__init__.py
lume/src/infrastructure/services/__init__.py
lume/src/infrastructure/services/executor/__init__.py
lume/src/infrastructure/services/executor/detach_popen_executor_service.py
lume/src/infrastructure/services/executor/fake_executor_service.py
lume/src/infrastructure/services/executor/popen_executor_service.py
lume/src/infrastructure/services/killer/__init__.py
lume/src/infrastructure/services/killer/fake_killer_service.py
lume/src/infrastructure/services/killer/popen_killer_service.py
lume/src/infrastructure/services/logger/__init__.py
lume/src/infrastructure/services/logger/colors.py
lume/src/infrastructure/services/logger/emojis_logger.py
lume/src/infrastructure/services/logger/fake_logger.py
lume/src/infrastructure/services/logger/not_implemented_logger.py
lume/src/infrastructure/services/logger/print_logger.py
lume/src/infrastructure/services/setup/__init__.py
lume-0.9.8.dist-info/LICENSE
lume-0.9.8.dist-info/METADATA
lume-0.9.8.dist-info/WHEEL
lume-0.9.8.dist-info/entry_points.txt
lume-0.9.8.dist-info/top_level.txt
lume-0.9.8.dist-info/RECORD
