Metadata-Version: 2.1
Name: lume
Version: 0.9.8
Summary: Lume
Home-page: https://github.com/alice-biometrics/lume
Author: Alice Biometrics
Author-email: support@alicebiometrics.com
License: MIT
Keywords: lume
Classifier: License :: OSI Approved :: MIT License
Classifier: Programming Language :: Python
Classifier: Programming Language :: Python :: 3
Classifier: Programming Language :: Python :: 3 :: Only
Classifier: Programming Language :: Python :: 3.8
Classifier: Programming Language :: Python :: 3.9
Classifier: Programming Language :: Python :: 3.10
Classifier: Programming Language :: Python :: 3.11
Classifier: Programming Language :: Python :: 3.12
License-File: LICENSE
Requires-Dist: meiga <2,>=1.5.0
Requires-Dist: pydantic <3
Requires-Dist: pyyaml <7
Requires-Dist: google-cloud-storage <3.0.0dev,>=1.32.0
Requires-Dist: google-api-core <3
Requires-Dist: protobuf <4,>=3.12.0
